simple_k8s_orm/__init__.py
simple_k8s_orm/base.py
simple_k8s_orm/orm.py
simple_k8s_orm/setup.py
simple_k8s_orm-0.1.0.dist-info/METADATA
simple_k8s_orm-0.1.0.dist-info/WHEEL
simple_k8s_orm-0.1.0.dist-info/top_level.txt
simple_k8s_orm-0.1.0.dist-info/RECORD
