Metadata-Version: 2.1
Name: simple-k8s-orm
Version: 0.1.0
Summary: Simple (probably) kubeapi ORM
Home-page: UNKNOWN
Author: Florian Baier
Author-email: f.baier1@gmail.com
License: UNKNOWN
Platform: UNKNOWN
Requires-Dist: kubernetes
Requires-Dist: requests
